bedrockz/__init__.py
bedrockz/__main__.py
bedrockz/_imports.py
bedrockz/cli.py
bedrockz/config.py
bedrockz/core.py
bedrockz/files.py
bedrockz/format.py
bedrockz/generator/example.py
bedrockz/generator/templates/brownie/token.py.jinja2
bedrockz-0.2.0.dist-info/entry_points.txt
bedrockz-0.2.0.dist-info/WHEEL
bedrockz-0.2.0.dist-info/METADATA
bedrockz-0.2.0.dist-info/RECORD
